fx2/__init__.py
fx2/boot-cypress.ihex
fx2/format.py
fx2/fx2tool.py
fx2-0.13.dist-info/METADATA
fx2-0.13.dist-info/WHEEL
fx2-0.13.dist-info/entry_points.txt
fx2-0.13.dist-info/top_level.txt
fx2-0.13.dist-info/RECORD
